CONTRIBUTING.rst
HISTORY.rst
LICENSE
MANIFEST.in
README.rst
android_controller.py
setup.cfg
setup.py
kupfer_plugin_android_controller.egg-info/PKG-INFO
kupfer_plugin_android_controller.egg-info/SOURCES.txt
kupfer_plugin_android_controller.egg-info/dependency_links.txt
kupfer_plugin_android_controller.egg-info/not-zip-safe
kupfer_plugin_android_controller.egg-info/top_level.txt